{"data":{"type":"discussions","id":"712","attributes":{"title":"HyeHosting sucks","slug":"712-hyehosting-sucks","commentCount":5,"participantCount":4,"createdAt":"2021-06-16T22:09:07+00:00","lastPostedAt":"2021-06-17T02:54:16+00:00","lastPostNumber":5,"canReply":true,"canRename":false,"canDelete":false,"canHide":false,"isApproved":true,"isSticky":false,"canSticky":false,"isLocked":false,"canLock":false,"canTag":false,"canSeeReactions":true,"canMerge":false},"relationships":{"posts":{"data":[{"type":"posts","id":"19048"},{"type":"posts","id":"19050"},{"type":"posts","id":"19059"},{"type":"posts","id":"19071"},{"type":"posts","id":"19076"}]},"tags":{"data":[{"type":"tags","id":"4"}]}}},"included":[{"type":"posts","id":"19048","attributes":{"number":1,"createdAt":"2021-06-16T22:09:07+00:00","contentType":"comment","contentHtml":"<p>i heard about hye hosting last year, looked unprofessional, and i let it fade away as i thought it was a summerhost<br>\nturns out i was right, it was a summerhost, because it faded away and disappeared, and now it has coincidentally came back during the start of summer time. im so excited to see how fast it will fade away before september<br>\nthey have their own \"custom control panel\" called the rat, turns out its just pterodactyl with a skin over it. they have their own \" n vps\" shit and its basically a lxc or openvz container that they renamed and modified. the lesson here is, hye hosting is shit, the owner acts professional in his little discord community but when privately speaking to him (spoke to him today multiple times) he lazy and unprofessional.</p>","canEdit":false,"canDelete":false,"canHide":false,"canLike":true,"canFlag":true,"isApproved":true,"canApprove":false,"canReact":true},"relationships":{"discussion":{"data":{"type":"discussions","id":"712"}},"user":{"data":{"type":"users","id":"3771"}},"likes":{"data":[]},"mentionedBy":{"data":[{"type":"posts","id":"19059"}]},"reactions":{"data":[]}}},{"type":"posts","id":"19059","attributes":{"number":3,"createdAt":"2021-06-16T22:22:32+00:00","contentType":"comment","contentHtml":"<blockquote class=\"uncited\"><div><p><a href=\"https://drama.gg/d/712/1\" class=\"PostMention\" data-id=\"19048\">anonymous0</a> \"custom control panel\" called the rat</p></div></blockquote>\n\n<p>lmfao i love this</p>","canEdit":false,"canDelete":false,"canHide":false,"canLike":true,"canFlag":true,"isApproved":true,"canApprove":false,"canReact":true},"relationships":{"user":{"data":{"type":"users","id":"50"}},"discussion":{"data":{"type":"discussions","id":"712"}},"likes":{"data":[]},"mentionedBy":{"data":[]},"reactions":{"data":[]}}},{"type":"posts","id":"19050","attributes":{"number":2,"createdAt":"2021-06-16T22:09:59+00:00","contentType":"comment","contentHtml":"<p>hi gavin how are you</p>","canEdit":false,"canDelete":false,"canHide":false,"canLike":true,"canFlag":true,"isApproved":true,"canApprove":false,"canReact":true},"relationships":{"discussion":{"data":{"type":"discussions","id":"712"}},"user":{"data":{"type":"users","id":"2836"}},"likes":{"data":[]},"mentionedBy":{"data":[]},"reactions":{"data":[{"type":"post_reactions","id":"568"}]}}},{"type":"posts","id":"19071","attributes":{"number":4,"createdAt":"2021-06-16T22:41:21+00:00","contentType":"comment","contentHtml":"<p><a href=\"https://drama.gg/u/Cian\" class=\"UserMention\">@Cian</a>  This one wasn't me.</p>","canEdit":false,"canDelete":false,"canHide":false,"canLike":true,"canFlag":true,"isApproved":true,"canApprove":false,"canReact":true},"relationships":{"discussion":{"data":{"type":"discussions","id":"712"}},"user":{"data":{"type":"users","id":"3711"}},"likes":{"data":[]},"mentionedBy":{"data":[]},"reactions":{"data":[]}}},{"type":"posts","id":"19076","attributes":{"number":5,"createdAt":"2021-06-17T02:54:16+00:00","contentType":"comment","contentHtml":"<p>My advice is to avoid hye hosting at all costs and use digitalocean or fastcomet.</p>","canEdit":false,"canDelete":false,"canHide":false,"canLike":true,"canFlag":true,"isApproved":true,"canApprove":false,"canReact":true},"relationships":{"discussion":{"data":{"type":"discussions","id":"712"}},"user":{"data":{"type":"users","id":"3771"}},"likes":{"data":[]},"mentionedBy":{"data":[]},"reactions":{"data":[]}}},{"type":"users","id":"3771","attributes":{"username":"anonymous0","displayName":"anonymous0","avatarUrl":null,"slug":"anonymous0","joinTime":"2021-06-05T14:13:49+00:00","discussionCount":1,"commentCount":20,"canEdit":false,"canDelete":false,"lastSeenAt":"2021-07-27T21:44:29+00:00","canSuspend":false,"canEditPolls":false,"canStartPolls":true,"canSelfEditPolls":true,"canVotePolls":true,"cover":null,"cover_thumbnail":null,"canSetProfileCover":false,"canEditOwnNickname":false,"bio":null,"canViewBio":true,"canEditBio":false},"relationships":{"groups":{"data":[]}}},{"type":"users","id":"50","attributes":{"username":"eraters","displayName":"eraters","avatarUrl":"https://drama.gg/assets/avatars/InBbUrIiLh2f1NZE.png","slug":"eraters","joinTime":"2020-07-27T00:18:18+00:00","discussionCount":9,"commentCount":475,"canEdit":false,"canDelete":false,"lastSeenAt":"2023-10-27T21:07:10+00:00","canSuspend":false,"canEditPolls":false,"canStartPolls":true,"canSelfEditPolls":true,"canVotePolls":true,"cover":"ElCZfR5C5zzACft3.jpg","cover_thumbnail":"thumbnails/ElCZfR5C5zzACft3.jpg","canSetProfileCover":false,"canEditOwnNickname":false,"bio":"e\ner\nera\nerat\nerate\nerater\neraters\nraters\naters\nters\ners\nrs\ns","canViewBio":true,"canEditBio":false},"relationships":{"groups":{"data":[]}}},{"type":"users","id":"2836","attributes":{"username":"Cian","displayName":"Cian","avatarUrl":"https://drama.gg/assets/avatars/sqIDGS1Db55kQ7J5.png","slug":"Cian","joinTime":"2020-09-28T03:51:51+00:00","discussionCount":4,"commentCount":45,"canEdit":false,"canDelete":false,"lastSeenAt":"2022-12-12T12:00:37+00:00","canSuspend":false,"canEditPolls":false,"canStartPolls":true,"canSelfEditPolls":true,"canVotePolls":true,"cover":null,"cover_thumbnail":null,"canSetProfileCover":false,"canEditOwnNickname":false,"bio":"Head of Customer Service at Hye Hosting LLC","canViewBio":true,"canEditBio":false},"relationships":{"groups":{"data":[]}}},{"type":"users","id":"3711","attributes":{"username":"Skie","displayName":"Skie","avatarUrl":"https://drama.gg/assets/avatars/OuGNIutPnmNj4JBk.png","slug":"Skie","joinTime":"2021-05-25T12:35:08+00:00","discussionCount":3,"commentCount":82,"canEdit":false,"canDelete":false,"lastSeenAt":"2021-07-03T20:48:54+00:00","canSuspend":false,"canEditPolls":false,"canStartPolls":true,"canSelfEditPolls":true,"canVotePolls":true,"cover":null,"cover_thumbnail":null,"canSetProfileCover":false,"canEditOwnNickname":false,"bio":null,"canViewBio":true,"canEditBio":false},"relationships":{"groups":{"data":[]}}},{"type":"post_reactions","id":"568","attributes":{"userId":3771,"postId":19050,"reactionId":7}},{"type":"tags","id":"4","attributes":{"name":"Discussion","description":"Threads which are open for discussion.","slug":"discussion","color":"#15d4a7","backgroundUrl":null,"backgroundMode":null,"icon":"far fa-comment-alt","discussionCount":479,"position":3,"defaultSort":null,"isChild":false,"isHidden":false,"lastPostedAt":"2023-10-24T17:32:49+00:00","canStartDiscussion":true,"canAddToDiscussion":true}}]}