{"data":{"type":"discussions","id":"813","attributes":{"title":"VyxterHost, Abusing AWS Trial, Lying to their members, and skidded addons.","slug":"813-vyxterhost-abusing-aws-trial-lying-to-their-members-and-skidded-addons","commentCount":30,"participantCount":11,"createdAt":"2021-07-16T18:19:23+00:00","lastPostedAt":"2021-12-16T06:16:40+00:00","lastPostNumber":36,"canReply":true,"canRename":false,"canDelete":false,"canHide":false,"isApproved":true,"isSticky":false,"canSticky":false,"isLocked":false,"canLock":false,"canTag":false,"canSeeReactions":true,"canMerge":false},"relationships":{"posts":{"data":[{"type":"posts","id":"21713"},{"type":"posts","id":"21714"},{"type":"posts","id":"21945"},{"type":"posts","id":"22017"},{"type":"posts","id":"22021"},{"type":"posts","id":"22025"},{"type":"posts","id":"22026"},{"type":"posts","id":"22027"},{"type":"posts","id":"22028"},{"type":"posts","id":"22029"},{"type":"posts","id":"22030"},{"type":"posts","id":"22031"},{"type":"posts","id":"22032"},{"type":"posts","id":"22033"},{"type":"posts","id":"22034"},{"type":"posts","id":"22036"},{"type":"posts","id":"22037"},{"type":"posts","id":"22038"},{"type":"posts","id":"22039"},{"type":"posts","id":"22040"},{"type":"posts","id":"22041"},{"type":"posts","id":"22042"},{"type":"posts","id":"22043"},{"type":"posts","id":"22044"},{"type":"posts","id":"22045"},{"type":"posts","id":"22057"},{"type":"posts","id":"22068"},{"type":"posts","id":"38180"},{"type":"posts","id":"38181"},{"type":"posts","id":"38182"}]},"tags":{"data":[{"type":"tags","id":"4"},{"type":"tags","id":"5"},{"type":"tags","id":"7"},{"type":"tags","id":"9"}]}}},"included":[{"type":"posts","id":"21713","attributes":{"number":1,"createdAt":"2021-07-16T18:19:23+00:00","contentType":"comment","contentHtml":"<p>Hello, so today, my friend and I were looking for some hostings to check on, and we found this particular one, which seemed very interesting.</p>\n\n<p>They lie to their members that they \"reset\" their nodes, but in reality, it's because their Amazon Free Trial ended.</p>\n\n<p>I cannot provide a screenshot of the dates, as they deleted it, but I noted them just in case, here is the list:</p>\n\n<ul><li>USAFREE1 &amp; USAFREE2: 17/7/21</li>\n<li>USAFREE3 &amp; USAFREE4: 10/08/21</li> </ul>\n\n<p>It's a Spanish host, so most of you won't understand the screenshots below, but I'll translate them for you. (I censored my friend's name as he wanted me to do so.)<br>\n<img src=\"https://drama.gg/assets/files/2021-07-16/1626459122-531469-captura-de-pantalla-2021-07-15-a-las-220258.png\" title=\"\"></p>\n\n<p>[+] The \"resets\" of your nodes, are they really reset or is it because your AWS Free Trial ends?<br>\n[-] Hahaha, both</p>\n\n<p>And here's proof that they use AWS Trial servers:<br>\n<img src=\"https://drama.gg/assets/files/2021-07-16/1626459287-890604-image.png\" title=\"\"><br>\nThey also allowed bash on their nodes, which allowed us to check more things:<br>\n<img src=\"https://drama.gg/assets/files/2021-07-16/1626459324-977516-image.png\" title=\"\"><br>\n1GB of RAM left on \"their node\",</p>\n\n<p>They also seemed to have skidded their pterodactyl addons, as they use AWS Free Trial.<br>\n<img src=\"https://drama.gg/assets/files/2021-07-16/1626459399-656826-image.png\" title=\"\"></p>\n\n<p>And this is out of context, but I also doubt they translated the <strong>WHOLE</strong> pterodactyl installation to Spanish by themselves.</p>\n\n<p><img src=\"https://drama.gg/assets/files/2021-07-16/1626459439-792734-image.png\" title=\"\"><br>\nThere's more, but this is what my friend sent me.</p>\n\n<p>They also removed Pterodactyl credits on the login page, like, lmao.</p>\n\n<p><img src=\"https://drama.gg/assets/files/2021-07-16/1626459495-373215-image.png\" title=\"\"></p>\n","editedAt":"2021-07-16T18:20:46+00:00","canEdit":false,"canDelete":false,"canHide":false,"canLike":true,"canFlag":true,"isApproved":true,"canApprove":false,"canReact":true},"relationships":{"discussion":{"data":{"type":"discussions","id":"813"}},"user":{"data":{"type":"users","id":"3427"}},"editedUser":{"data":{"type":"users","id":"3427"}},"likes":{"data":[]},"mentionedBy":{"data":[{"type":"posts","id":"22045"},{"type":"posts","id":"22057"}]},"reactions":{"data":[]}}},{"type":"posts","id":"22045","attributes":{"number":31,"createdAt":"2021-07-20T23:42:52+00:00","contentType":"comment","contentHtml":"<p><a href=\"https://drama.gg/d/813/1\" class=\"PostMention\" data-id=\"21713\">babyharpseal</a> and the proof of the addons? <br>\ni was watching and i did confirm for myself that they use aws. still, what's the problem? are they paying you to defend them? lmaoo<br>\nand if I am still in doubt about the modifications, I will try to communicate to a staff member on the thread so that he/she can answer .</p>\n"},"relationships":{"user":{"data":{"type":"users","id":"4017"}},"discussion":{"data":{"type":"discussions","id":"813"}}}},{"type":"posts","id":"22057","attributes":{"number":32,"createdAt":"2021-07-21T04:14:16+00:00","contentType":"comment","contentHtml":"<p>Hola muy buenas, soy el ceo de dicho host. Mi idioma es español y así hablare, al que le importe lo traducirá y se las arregla, pero no me molesto total los que hicieron el hilo son españoles así que entenderán, mi mensaje va para ellos.</p>\n\n<p>Voy a empezar respondiendo la primer línea</p>\n<blockquote class=\"uncited\"><div><p><a href=\"https://drama.gg/d/813/1\" class=\"PostMention\" data-id=\"21713\">babyharpseal</a> hoy, mi amigo y yo estábamos buscando algunos hostings para revisar<br>\nAl menos si van a mentir, mientan bien. Tu amigo y tu, se unieron el 10/7. Así que wow increíble busqueda de hoy.<br>\n<img src=\"https://drama.gg/assets/files/2021-07-21/1626839232-160514-image.png\" title=\"\"><br>\n<img src=\"https://drama.gg/assets/files/2021-07-21/1626839414-300131-image.png\" title=\"\"></p></div></blockquote>\n\n<p>Ahora si comencemos.</p> \n\n<p>.</p>\n<blockquote class=\"uncited\"><div><p><a href=\"https://drama.gg/d/813/1\" class=\"PostMention\" data-id=\"21713\">babyharpseal</a> (Censuré el nombre de mi amigo porque él quería que lo hiciera).</p></div></blockquote>\n\n<p>Acá revelamos la conversación completa, y desde acá, willy por mi parte sinceramente, me cago en lo que usas tu \"con confianza.\" enserio que contaba con vos y todo, y que te regales así wow, sos como todos los hilos que hay aquí lo dicen. Sin palabras.<br>\n<img src=\"https://drama.gg/assets/files/2021-07-21/1626839612-406193-image.png\" title=\"\"><br>\nPara los que no entiendan que dice, simplemente me esta haciendo la pregunta que leyeron, pero antes de eso me dijo, con confianza. Refiriéndose a que la pregunta es entre nosotros o \"amistad\".</p>\n\n<blockquote class=\"uncited\"><div><p><a href=\"https://drama.gg/d/813/1\" class=\"PostMention\" data-id=\"21713\">babyharpseal</a> Y aquí está la prueba de que usan servidores AWS Trial:</p></div></blockquote>\n\n<p>Aws usamos, yo no miento. Pero en que te afecta me explicas? Acaso te hago algo teniéndolo? A ya se, acaso te arde ver como crezco y es el único punto débil que tengo y por eso lo usas? Te comento rey, estamos usando ese servicio por que aun no tenemos presupuesto, pero ni te preocupes en nosotros en serio muchísimas gracias por tanta atención, pero si tranquilo ya estamos consiguiendo dinero para comprarnos nuestra propia maquina para no tener problemas, pero enserio gracias por tu preocupación ya no hace falta.</p> \n\n<blockquote class=\"uncited\"><div><p><a href=\"https://drama.gg/d/813/1\" class=\"PostMention\" data-id=\"21713\">babyharpseal</a> Y esto está fuera de contexto, pero también dudo que hayan traducido TODA la instalación de pterodáctilo al español por sí mismos.</p></div></blockquote>\n\n<p>Enserio me cago de risa al leer esto, acaso no sabes dedicarle todo tu tiempo y cariño para hacer algo bien? Bueno eso hice yo, este proyecto llevaba escondido mas tiempo de lo que piensas, por eso iniciamos tan bien, estaba todo completo, como cualquier empresa tiene que ser, encontraras algo malo? No lo hay cierto? Ese es el resultado de todo mi tiempo trabajando.</p>\n\n<blockquote class=\"uncited\"><div><p><a href=\"https://drama.gg/d/813/1\" class=\"PostMention\" data-id=\"21713\">babyharpseal</a> También eliminaron los créditos de Pterodactyl en la página de inicio de sesión, como, lmao.</p></div></blockquote>\n\n<p>Comencemos con que te informes, es legal cambiar los créditos, reportas y ni sabes eso simplemente dice que solo haces esto por ardido o por que algo te molesta de mi y no la empresa, te delatas solo.<br>\nY no tranquilo, te comento que les damos créditos aunque no es necesario.<br>\n<img src=\"https://drama.gg/assets/files/2021-07-21/1626840074-668560-image.png\" title=\"\"></p>\n\n<blockquote class=\"uncited\"><div><p><a href=\"https://drama.gg/d/813/2\" class=\"PostMention\" data-id=\"21714\">babyharpseal</a> Captura de pantalla de su panel que encontré en su servidor Discord:</p></div></blockquote>\n\n<p>Gracias por mostrar todo mi trabajo, acaso te enamoraste?</p> \n\n<blockquote class=\"uncited\"><div><p><a href=\"https://drama.gg/d/813/1\" class=\"PostMention\" data-id=\"21713\">babyharpseal</a> También parecían haber derrapado sus complementos de pterodáctilo, ya que utilizan la prueba gratuita de AWS.</p></div></blockquote>\n\n<p>Y mira rey, yo no tengo ningún derecho a mostrarte en que invirtiendo, pero para que se te acabe el ego y te pongas en tu lugar, todos los plugins los compramos nosotros, y seguiremos haciéndolo, te enseño para que? MEJORAR, y no quedarse estancado. Anota. (El de upload por si tan interesado estas lo compro mi compañero directamente al vendedor, así que te la debo rey).<br>\n <img src=\"https://drama.gg/assets/files/2021-07-21/1626840379-307353-image.png\" title=\"\"></p>\n\n<p>Despues de decir esto y cerrarte bien el orto, me retiro y no vuelvo por aca, zona mas toxica imposible, pero que manchen mi empresa con estupideces de niños no lo dejare, gracias y buenas noches. <br>\nY gracias a los dos @LlamaradaPhoenix <a href=\"https://drama.gg/u/_Caiu_\" class=\"UserMention\">@_Caiu_</a> que entienden la situación.<br>\nUn gusto despejar dudas, cuídense y baby, suerte en tu host, recomiendo que le des importancia a las cosas que son tuyas y no meterte donde no te llaman.</p> \n\n<p><a href=\"https://drama.gg/u/Jedrik\" class=\"UserMention\">@Jedrik</a> Sorry to mention it, if you can then close this unnecessary thread I would be grateful.</p>\n\n\n\n\n\n\n\n"},"relationships":{"user":{"data":{"type":"users","id":"3536"}},"discussion":{"data":{"type":"discussions","id":"813"}}}},{"type":"posts","id":"21714","attributes":{"number":2,"createdAt":"2021-07-16T18:24:45+00:00","contentType":"comment","contentHtml":"<p>Screenshot of their panel which I found on their Discord server: <img src=\"https://drama.gg/assets/files/2021-07-16/1626459882-971308-image.png\" title=\"\"></p>\n","canEdit":false,"canDelete":false,"canHide":false,"canLike":true,"canFlag":true,"isApproved":true,"canApprove":false,"canReact":true},"relationships":{"discussion":{"data":{"type":"discussions","id":"813"}},"user":{"data":{"type":"users","id":"3427"}},"likes":{"data":[]},"mentionedBy":{"data":[{"type":"posts","id":"22057"}]},"reactions":{"data":[]}}},{"type":"posts","id":"21945","attributes":{"number":7,"createdAt":"2021-07-19T21:21:02+00:00","contentType":"comment","contentHtml":"<p>First of all, where does it say you can remove it's credits?<br>\nSecond, there's no proof, but if they don't pay for nodes and abuse AWS, I doubt they bought the addons</p>","canEdit":false,"canDelete":false,"canHide":false,"canLike":true,"canFlag":true,"isApproved":true,"canApprove":false,"canReact":true},"relationships":{"discussion":{"data":{"type":"discussions","id":"813"}},"user":{"data":{"type":"users","id":"3427"}},"likes":{"data":[]},"mentionedBy":{"data":[]},"reactions":{"data":[]}}},{"type":"posts","id":"22017","attributes":{"number":9,"createdAt":"2021-07-20T17:56:22+00:00","contentType":"comment","contentHtml":"<p><a href=\"https://drama.gg/d/813/3\" class=\"PostMention\" data-id=\"21847\">Willypro7</a> It will be because nobody cares, at least I am in it and they give me good support.<br>\nBetter notice that they copied the XD host in my profile, you have the thread haha</p>","canEdit":false,"canDelete":false,"canHide":false,"canLike":true,"canFlag":true,"isApproved":true,"canApprove":false,"canReact":true},"relationships":{"discussion":{"data":{"type":"discussions","id":"813"}},"user":{"data":{"type":"users","id":"4017"}},"likes":{"data":[]},"mentionedBy":{"data":[{"type":"posts","id":"22026"},{"type":"posts","id":"22038"}]},"reactions":{"data":[]}}},{"type":"posts","id":"22026","attributes":{"number":13,"createdAt":"2021-07-20T19:18:27+00:00","contentType":"comment","contentHtml":"<p><a href=\"https://drama.gg/d/813/9\" class=\"PostMention\" data-id=\"22017\">_Caiu_</a> Can already tell you some drama.gg people <strong>do</strong> care lol</p>","canEdit":false,"canDelete":false,"canHide":false,"canLike":true,"canFlag":true,"isApproved":true,"canApprove":false,"canReact":true},"relationships":{"user":{"data":{"type":"users","id":"3427"}},"discussion":{"data":{"type":"discussions","id":"813"}},"likes":{"data":[]},"mentionedBy":{"data":[{"type":"posts","id":"22027"}]},"reactions":{"data":[]}}},{"type":"posts","id":"22038","attributes":{"number":24,"createdAt":"2021-07-20T20:16:49+00:00","contentType":"comment","contentHtml":"<p><a href=\"https://drama.gg/d/813/9\" class=\"PostMention\" data-id=\"22017\">_Caiu_</a> Learn ingles, and then talk, you have even worst English than me</p> ","canEdit":false,"canDelete":false,"canHide":false,"canLike":true,"canFlag":true,"isApproved":true,"canApprove":false,"canReact":true},"relationships":{"user":{"data":{"type":"users","id":"3291"}},"discussion":{"data":{"type":"discussions","id":"813"}},"likes":{"data":[]},"mentionedBy":{"data":[{"type":"posts","id":"22044"}]},"reactions":{"data":[]}}},{"type":"posts","id":"22021","attributes":{"number":10,"createdAt":"2021-07-20T18:00:04+00:00","contentType":"comment","contentHtml":"<p>Tremendo lo que hacen por querer \"tumbar\" un host. Y no lo digo dizque porque de cierta manera trabajo alli. Sino porque es cierto, los unicos que se lucran de esta informacion es a otros hostings. Y segun se, vos tenes uno.</p>\n\n<p>Tampoco hay necesidad de poner lo de la firma de Pterodactyl en el Footer, si como dijo alguien de arriba esta permitido.</p>\n\n<p>Al igual que con el tema de AWS. Si lo utilizamos es por el presupuesto que tenemos. Sino ya nos verias con Nodos proporcionados por OVH, Contabo, etc.</p>","canEdit":false,"canDelete":false,"canHide":false,"canLike":true,"canFlag":true,"isApproved":true,"canApprove":false,"canReact":true},"relationships":{"discussion":{"data":{"type":"discussions","id":"813"}},"user":{"data":{"type":"users","id":"4020"}},"likes":{"data":[{"type":"users","id":"3071"}]},"mentionedBy":{"data":[{"type":"posts","id":"22025"},{"type":"posts","id":"22037"},{"type":"posts","id":"22068"}]},"reactions":{"data":[]}}},{"type":"posts","id":"22025","attributes":{"number":12,"createdAt":"2021-07-20T19:11:11+00:00","contentType":"comment","contentHtml":"<p><a href=\"https://drama.gg/d/813/10\" class=\"PostMention\" data-id=\"22021\">RaymondG</a> Si, yo tengo un hosting, pero al menos es legal.</p>","canEdit":false,"canDelete":false,"canHide":false,"canLike":true,"canFlag":true,"isApproved":true,"canApprove":false,"canReact":true},"relationships":{"user":{"data":{"type":"users","id":"3427"}},"discussion":{"data":{"type":"discussions","id":"813"}},"likes":{"data":[]},"mentionedBy":{"data":[{"type":"posts","id":"22029"}]},"reactions":{"data":[]}}},{"type":"posts","id":"22037","attributes":{"number":23,"createdAt":"2021-07-20T20:15:39+00:00","contentType":"comment","contentHtml":"<blockquote class=\"uncited\"><div><p><a href=\"https://drama.gg/d/813/10\" class=\"PostMention\" data-id=\"22021\">RaymondG</a> Al igual que con el tema de AWS. Si lo utilizamos es por el presupuesto que tenemos. Sino ya nos verias con Nodos proporcionados por OVH, Contabo, etc.</p></div></blockquote>\n\n<p>Bruh tus nodos son los gratuitos de aws, el mismo owner lo admitió en esa captura<br>\n// <br>\nBruh you use aws free nodes, the owner admitted to do it</p>\n","canEdit":false,"canDelete":false,"canHide":false,"canLike":true,"canFlag":true,"isApproved":true,"canApprove":false,"canReact":true},"relationships":{"user":{"data":{"type":"users","id":"3291"}},"discussion":{"data":{"type":"discussions","id":"813"}},"likes":{"data":[]},"mentionedBy":{"data":[{"type":"posts","id":"22039"},{"type":"posts","id":"22042"}]},"reactions":{"data":[]}}},{"type":"posts","id":"22068","attributes":{"number":33,"createdAt":"2021-07-21T06:54:10+00:00","contentType":"comment","contentHtml":"<p><a href=\"https://drama.gg/d/813/10\" class=\"PostMention\" data-id=\"22021\">RaymondG</a> A ver, seré sincera. No deberían empezar un hosting sin presupuesto, <strong>nunca</strong>, esto lo sé por experiencia desde 2017. De todas maneras, conseguir servidores baratos (y buenos) no es tan difícil, echenle un poco de esfuerzo. Hablando de AWS, supongo que es \"ilegal\"? No sé cómo funcionará lo que hacen, tampoco me importa, pero la cosa es la legalidad de eso. Al menos les doy un punto adicional por no abusar Azure como cualquier \"\"hosting\"\" promedio latinoamericano hecho por un niño de 10 años. Les deseo suerte y les recomiendo nuevamente invertir un <em>poquito</em> de plata, será la mejor decisión, se los aseguro.</p>\n\n<p>Ahora es momento de volverme gringa nuevamente.</p>"},"relationships":{"user":{"data":{"type":"users","id":"3126"}},"discussion":{"data":{"type":"discussions","id":"813"}}}},{"type":"posts","id":"22029","attributes":{"number":16,"createdAt":"2021-07-20T19:23:12+00:00","contentType":"comment","contentHtml":"<p><a href=\"https://drama.gg/d/813/12\" class=\"PostMention\" data-id=\"22025\">babyharpseal</a> hahahahahah, which is your host? I would like to see it.</p>\n\n<p>hey if it's moonhost that doesn't count as a company or host hahaha, led by kids, not even a stable page with cough hahahahah don't make me laugh</p>","canEdit":false,"canDelete":false,"canHide":false,"canLike":true,"canFlag":true,"isApproved":true,"canApprove":false,"canReact":true},"relationships":{"user":{"data":{"type":"users","id":"4017"}},"discussion":{"data":{"type":"discussions","id":"813"}},"likes":{"data":[]},"mentionedBy":{"data":[]},"reactions":{"data":[]}}},{"type":"posts","id":"22027","attributes":{"number":14,"createdAt":"2021-07-20T19:22:01+00:00","contentType":"comment","contentHtml":"<p><a href=\"https://drama.gg/d/813/13\" class=\"PostMention\" data-id=\"22026\">babyharpseal</a> hey excuse me, your google translator makes me not understand, what do you mean?</p>","canEdit":false,"canDelete":false,"canHide":false,"canLike":true,"canFlag":true,"isApproved":true,"canApprove":false,"canReact":true},"relationships":{"user":{"data":{"type":"users","id":"4017"}},"discussion":{"data":{"type":"discussions","id":"813"}},"likes":{"data":[]},"mentionedBy":{"data":[]},"reactions":{"data":[]}}},{"type":"posts","id":"22028","attributes":{"number":15,"createdAt":"2021-07-20T19:22:47+00:00","contentType":"comment","contentHtml":"<p>Wdym with Google translator</p> ","canEdit":false,"canDelete":false,"canHide":false,"canLike":true,"canFlag":true,"isApproved":true,"canApprove":false,"canReact":true},"relationships":{"discussion":{"data":{"type":"discussions","id":"813"}},"user":{"data":{"type":"users","id":"3427"}},"likes":{"data":[]},"mentionedBy":{"data":[{"type":"posts","id":"22031"}]},"reactions":{"data":[]}}},{"type":"posts","id":"22031","attributes":{"number":18,"createdAt":"2021-07-20T19:24:22+00:00","contentType":"comment","contentHtml":"<p><a href=\"https://drama.gg/d/813/15\" class=\"PostMention\" data-id=\"22028\">babyharpseal</a> you are going to tell me what you meant, try to use something better at least if you dont know english v:</p>","canEdit":false,"canDelete":false,"canHide":false,"canLike":true,"canFlag":true,"isApproved":true,"canApprove":false,"canReact":true},"relationships":{"user":{"data":{"type":"users","id":"4017"}},"discussion":{"data":{"type":"discussions","id":"813"}},"likes":{"data":[]},"mentionedBy":{"data":[{"type":"posts","id":"22032"}]},"reactions":{"data":[]}}},{"type":"posts","id":"22030","attributes":{"number":17,"createdAt":"2021-07-20T19:24:21+00:00","contentType":"comment","contentHtml":"<p>1- <a href=\"https://galaxynodes.xyz\" rel=\" nofollow ugc\">https://galaxynodes.xyz</a><br>\n2- No, it isn't Moonhost.</p>","canEdit":false,"canDelete":false,"canHide":false,"canLike":true,"canFlag":true,"isApproved":true,"canApprove":false,"canReact":true},"relationships":{"discussion":{"data":{"type":"discussions","id":"813"}},"user":{"data":{"type":"users","id":"3427"}},"likes":{"data":[]},"mentionedBy":{"data":[{"type":"posts","id":"22033"}]},"reactions":{"data":[]}}},{"type":"posts","id":"22033","attributes":{"number":20,"createdAt":"2021-07-20T19:26:58+00:00","contentType":"comment","contentHtml":"<p><a href=\"https://drama.gg/d/813/17\" class=\"PostMention\" data-id=\"22030\">babyharpseal</a> great page, do you have the receipt of purchase of that style 🙂</p>\n","canEdit":false,"canDelete":false,"canHide":false,"canLike":true,"canFlag":true,"isApproved":true,"canApprove":false,"canReact":true},"relationships":{"user":{"data":{"type":"users","id":"4017"}},"discussion":{"data":{"type":"discussions","id":"813"}},"likes":{"data":[]},"mentionedBy":{"data":[{"type":"posts","id":"22034"}]},"reactions":{"data":[]}}},{"type":"posts","id":"22032","attributes":{"number":19,"createdAt":"2021-07-20T19:25:11+00:00","contentType":"comment","contentHtml":"<p><a href=\"https://drama.gg/d/813/18\" class=\"PostMention\" data-id=\"22031\">_Caiu_</a> I know English wdym, but it's not my first language and I may have some spelling errors</p>","editedAt":"2021-07-20T19:25:42+00:00","canEdit":false,"canDelete":false,"canHide":false,"canLike":true,"canFlag":true,"isApproved":true,"canApprove":false,"canReact":true},"relationships":{"user":{"data":{"type":"users","id":"3427"}},"discussion":{"data":{"type":"discussions","id":"813"}},"editedUser":{"data":{"type":"users","id":"3427"}},"likes":{"data":[{"type":"users","id":"4017"}]},"mentionedBy":{"data":[]},"reactions":{"data":[{"type":"post_reactions","id":"730"}]}}},{"type":"posts","id":"22034","attributes":{"number":21,"createdAt":"2021-07-20T19:27:35+00:00","contentType":"comment","contentHtml":"<p><a href=\"https://drama.gg/d/813/20\" class=\"PostMention\" data-id=\"22033\">_Caiu_</a> I currently don't as the other owner bought it but he's currently on vacation</p>","canEdit":false,"canDelete":false,"canHide":false,"canLike":true,"canFlag":true,"isApproved":true,"canApprove":false,"canReact":true},"relationships":{"user":{"data":{"type":"users","id":"3427"}},"discussion":{"data":{"type":"discussions","id":"813"}},"likes":{"data":[]},"mentionedBy":{"data":[]},"reactions":{"data":[]}}},{"type":"posts","id":"22036","attributes":{"number":22,"createdAt":"2021-07-20T19:59:43+00:00","contentType":"comment","contentHtml":"<p>oh im late lmao</p>","canEdit":false,"canDelete":false,"canHide":false,"canLike":true,"canFlag":true,"isApproved":true,"canApprove":false,"canReact":true},"relationships":{"discussion":{"data":{"type":"discussions","id":"813"}},"user":{"data":{"type":"users","id":"3639"}},"likes":{"data":[]},"mentionedBy":{"data":[]},"reactions":{"data":[]}}},{"type":"posts","id":"22039","attributes":{"number":25,"createdAt":"2021-07-20T20:20:52+00:00","contentType":"comment","contentHtml":"<p><a href=\"https://drama.gg/d/813/23\" class=\"PostMention\" data-id=\"22037\">Willypro7</a> please can you  translate that to english for me</p>","editedAt":"2021-07-20T20:21:38+00:00","canEdit":false,"canDelete":false,"canHide":false,"canLike":true,"canFlag":true,"isApproved":true,"canApprove":false,"canReact":true},"relationships":{"user":{"data":{"type":"users","id":"3822"}},"discussion":{"data":{"type":"discussions","id":"813"}},"editedUser":{"data":{"type":"users","id":"3822"}},"likes":{"data":[]},"mentionedBy":{"data":[{"type":"posts","id":"22040"}]},"reactions":{"data":[]}}},{"type":"posts","id":"22042","attributes":{"number":28,"createdAt":"2021-07-20T20:29:17+00:00","contentType":"comment","contentHtml":"<p><a href=\"https://drama.gg/d/813/23\" class=\"PostMention\" data-id=\"22037\">Willypro7</a> this</p>"},"relationships":{"user":{"data":{"type":"users","id":"3822"}},"discussion":{"data":{"type":"discussions","id":"813"}}}},{"type":"posts","id":"22044","attributes":{"number":30,"createdAt":"2021-07-20T22:40:47+00:00","contentType":"comment","contentHtml":"<p><a href=\"https://drama.gg/d/813/24\" class=\"PostMention\" data-id=\"22038\">Willypro7</a> hey dont get mad kid 😆</p> "},"relationships":{"user":{"data":{"type":"users","id":"4017"}},"discussion":{"data":{"type":"discussions","id":"813"}}}},{"type":"posts","id":"22040","attributes":{"number":26,"createdAt":"2021-07-20T20:22:51+00:00","contentType":"comment","contentHtml":"<p><a href=\"https://drama.gg/d/813/25\" class=\"PostMention\" data-id=\"22039\">CancelledCactus</a> Bruh you use aws free nodes, the owner admitted to do it, <br>\n<img src=\"https://drama.gg/assets/files/2021-07-20/1626812568-503831-image.png\" title=\"\"></p>\n","canEdit":false,"canDelete":false,"canHide":false,"canLike":true,"canFlag":true,"isApproved":true,"canApprove":false,"canReact":true},"relationships":{"user":{"data":{"type":"users","id":"3291"}},"discussion":{"data":{"type":"discussions","id":"813"}},"likes":{"data":[]},"mentionedBy":{"data":[{"type":"posts","id":"22041"}]},"reactions":{"data":[]}}},{"type":"posts","id":"22041","attributes":{"number":27,"createdAt":"2021-07-20T20:29:01+00:00","contentType":"comment","contentHtml":"<p><a href=\"https://drama.gg/d/813/26\" class=\"PostMention\" data-id=\"22040\">Willypro7</a> no I said translate the other one</p>\n"},"relationships":{"user":{"data":{"type":"users","id":"3822"}},"discussion":{"data":{"type":"discussions","id":"813"}}}},{"type":"users","id":"3427","attributes":{"username":"babyharpseal","displayName":"babyharpseal","avatarUrl":"https://drama.gg/assets/avatars/gIjyTXWXF9yBA4uq.png","slug":"babyharpseal","joinTime":"2021-04-21T14:45:49+00:00","discussionCount":6,"commentCount":77,"canEdit":false,"canDelete":false,"lastSeenAt":"2023-03-11T11:22:59+00:00","canSuspend":false,"canEditPolls":false,"canStartPolls":true,"canSelfEditPolls":true,"canVotePolls":true,"cover":null,"cover_thumbnail":null,"canSetProfileCover":false,"canEditOwnNickname":false,"bio":null,"canViewBio":true,"canEditBio":false},"relationships":{"groups":{"data":[]}}},{"type":"users","id":"4017","attributes":{"username":"_Caiu_","displayName":"_Caiu_","avatarUrl":"https://drama.gg/assets/avatars/f9GSLdYfHSt5Yx5Q.png","slug":"_Caiu_","joinTime":"2021-07-20T03:30:32+00:00","discussionCount":1,"commentCount":13,"canEdit":false,"canDelete":false,"lastSeenAt":"2021-08-10T02:53:01+00:00","canSuspend":false,"canEditPolls":false,"canStartPolls":true,"canSelfEditPolls":true,"canVotePolls":true,"cover":null,"cover_thumbnail":null,"canSetProfileCover":false,"canEditOwnNickname":false,"bio":null,"canViewBio":true,"canEditBio":false},"relationships":{"groups":{"data":[]}}},{"type":"users","id":"3536","attributes":{"username":"AdrianWN","displayName":"AdrianWN","avatarUrl":null,"slug":"AdrianWN"}},{"type":"users","id":"3291","attributes":{"username":"Willypro7","displayName":"Willypro7","avatarUrl":"https://drama.gg/assets/avatars/6ejKNQiaajcKH8Zi.png","slug":"Willypro7","joinTime":"2021-03-29T16:39:19+00:00","discussionCount":1,"commentCount":172,"canEdit":false,"canDelete":false,"lastSeenAt":"2022-07-24T13:34:58+00:00","canSuspend":false,"canEditPolls":false,"canStartPolls":true,"canSelfEditPolls":true,"canVotePolls":true,"cover":null,"cover_thumbnail":null,"canSetProfileCover":false,"canEditOwnNickname":false,"bio":"Lol","canViewBio":true,"canEditBio":false},"relationships":{"groups":{"data":[]}}},{"type":"users","id":"4020","attributes":{"username":"RaymondG","displayName":"RaymondG","avatarUrl":"https://drama.gg/assets/avatars/TKE8qwPDvz4CBxdy.png","slug":"RaymondG","joinTime":"2021-07-20T17:47:27+00:00","discussionCount":0,"commentCount":1,"canEdit":false,"canDelete":false,"lastSeenAt":"2021-07-20T18:04:43+00:00","canSuspend":false,"canEditPolls":false,"canStartPolls":true,"canSelfEditPolls":true,"canVotePolls":true,"cover":null,"cover_thumbnail":null,"canSetProfileCover":false,"canEditOwnNickname":false,"bio":null,"canViewBio":true,"canEditBio":false},"relationships":{"groups":{"data":[]}}},{"type":"users","id":"3071","attributes":{"username":"FlaringPhoenix","displayName":"FlaringPhoenix","avatarUrl":"https://drama.gg/assets/avatars/5tCbptj67vHJs3SZ.png","slug":"FlaringPhoenix"}},{"type":"users","id":"3126","attributes":{"username":"exelen","displayName":"exelen","avatarUrl":"https://drama.gg/assets/avatars/qFR5MC7QLzE720NW.png","slug":"exelen"}},{"type":"users","id":"3639","attributes":{"username":"MaiDub","displayName":"MaiDub","avatarUrl":"https://drama.gg/assets/avatars/zBomDSWkdsG0S3g4.png","slug":"MaiDub","joinTime":"2021-05-16T18:44:30+00:00","discussionCount":3,"commentCount":15,"canEdit":false,"canDelete":false,"lastSeenAt":"2021-08-30T00:38:11+00:00","canSuspend":false,"canEditPolls":false,"canStartPolls":true,"canSelfEditPolls":true,"canVotePolls":true,"cover":null,"cover_thumbnail":null,"canSetProfileCover":false,"canEditOwnNickname":false,"bio":null,"canViewBio":true,"canEditBio":false},"relationships":{"groups":{"data":[]}}},{"type":"users","id":"3822","attributes":{"username":"CancelledCactus","displayName":"CancelledCactus","avatarUrl":"https://drama.gg/assets/avatars/fW2PAZdXHCRjmPKJ.png","slug":"CancelledCactus","joinTime":"2021-06-16T19:47:49+00:00","discussionCount":0,"commentCount":9,"canEdit":false,"canDelete":false,"lastSeenAt":"2021-08-02T19:47:42+00:00","canSuspend":false,"canEditPolls":false,"canStartPolls":true,"canSelfEditPolls":true,"canVotePolls":true,"cover":null,"cover_thumbnail":null,"canSetProfileCover":false,"canEditOwnNickname":false,"bio":null,"canViewBio":true,"canEditBio":false},"relationships":{"groups":{"data":[]}}},{"type":"post_reactions","id":"730","attributes":{"userId":4017,"postId":22032,"reactionId":1}},{"type":"tags","id":"4","attributes":{"name":"Discussion","description":"Threads which are open for discussion.","slug":"discussion","color":"#15d4a7","backgroundUrl":null,"backgroundMode":null,"icon":"far fa-comment-alt","discussionCount":479,"position":3,"defaultSort":null,"isChild":false,"isHidden":false,"lastPostedAt":"2023-10-24T17:32:49+00:00","canStartDiscussion":true,"canAddToDiscussion":true}},{"type":"tags","id":"5","attributes":{"name":"More","description":"Other tags.","slug":"more","color":"#15d4a7","backgroundUrl":null,"backgroundMode":null,"icon":"fas fa-ellipsis-h","discussionCount":593,"position":4,"defaultSort":null,"isChild":false,"isHidden":false,"lastPostedAt":"2023-10-27T21:11:23+00:00","canStartDiscussion":true,"canAddToDiscussion":true}},{"type":"tags","id":"7","attributes":{"name":"Illegal Activities","description":"People or companies which perform illegal activities such as fraud, all kinds of cybercrime, and more.","slug":"illegal-activities","color":"#15d4a7","backgroundUrl":null,"backgroundMode":null,"icon":"","discussionCount":302,"position":2,"defaultSort":null,"isChild":true,"isHidden":false,"lastPostedAt":"2023-10-26T16:27:59+00:00","canStartDiscussion":true,"canAddToDiscussion":true}},{"type":"tags","id":"9","attributes":{"name":"Bad Services","description":"People or organizations which offer a poor service.","slug":"bad","color":"#15d4a7","backgroundUrl":null,"backgroundMode":null,"icon":"","discussionCount":312,"position":3,"defaultSort":null,"isChild":true,"isHidden":false,"lastPostedAt":"2023-09-26T15:17:33+00:00","canStartDiscussion":true,"canAddToDiscussion":true}}]}