{"data":{"type":"posts","id":"10996","attributes":{"number":7,"createdAt":"2021-04-16T05:15:10+00:00","contentType":"comment","contentHtml":"<p><img src=\"https://drama.gg/assets/files/2021-04-16/1618549923-80613-image.png\" title=\"\"><br>\nGrammar is awful for the rules not generated by discord.</p>\n\n<p><img src=\"https://drama.gg/assets/files/2021-04-16/1618549982-85018-image.png\" title=\"\"><br>\nWhat is wrong... I mean yes, he made my server but not my tos or privacy policy. Now he edited the tos so I can't say anything...</p>","canEdit":false,"canDelete":false,"canHide":false,"canLike":true,"canFlag":true,"isApproved":true,"canApprove":false,"canReact":true},"relationships":{"user":{"data":{"type":"users","id":"3212"}},"discussion":{"data":{"type":"discussions","id":"374"}},"likes":{"data":[]},"mentionedBy":{"data":[]},"reactions":{"data":[]}}},"included":[{"type":"users","id":"3212","attributes":{"username":"DavidSaguna","displayName":"DavidSaguna","avatarUrl":"https://drama.gg/assets/avatars/gqjJJYg16KAaytMd.png","slug":"DavidSaguna","joinTime":"2021-03-15T16:55:21+00:00","discussionCount":0,"commentCount":17,"canEdit":false,"canDelete":false,"lastSeenAt":"2021-08-30T15:02:25+00:00","canSuspend":false,"canEditPolls":false,"canStartPolls":true,"canSelfEditPolls":true,"canVotePolls":true,"cover":null,"cover_thumbnail":null,"canSetProfileCover":false,"canEditOwnNickname":false,"bio":null,"canViewBio":true,"canEditBio":false},"relationships":{"groups":{"data":[]}}},{"type":"discussions","id":"374","attributes":{"title":"Better-Host, Falconodes - Nulled WHMCS","slug":"374-better-host-falconodes-nulled-whmcs","isApproved":true}}]}