{"data":{"type":"posts","id":"13243","attributes":{"number":13,"createdAt":"2021-05-04T08:05:34+00:00","contentType":"comment","contentHtml":"<p>Franklin Clinton account is EpicJuicy</p>","canEdit":false,"canDelete":false,"canHide":false,"canLike":true,"canFlag":true,"isApproved":true,"canApprove":false,"canReact":true},"relationships":{"discussion":{"data":{"type":"discussions","id":"448"}},"likes":{"data":[]},"mentionedBy":{"data":[]},"reactions":{"data":[]}}},"included":[{"type":"discussions","id":"448","attributes":{"title":"EpicJuicy#4950 has nuked OceanNodes.com","slug":"448-epicjuicy4950-has-nuked-oceannodescom","isApproved":true}}]}