{"data":{"type":"posts","id":"17299","attributes":{"number":61,"createdAt":"2021-05-29T20:43:52+00:00","contentType":"comment","contentHtml":"<p><a href=\"https://drama.gg/d/578/59\" class=\"PostMention\" data-id=\"17297\">ShamsPlays</a> i didnt say make me manager after you demoted me, i said will i get back role.<br>\nYou said no and i said ok.<br>\nAnd i said i will continue the thread and get it confirmed.<br>\nMy plan was not to winterhoax you my plan was to help host to fix all atiff and get it better, alphy is just a stupid guy.<br>\nAnd also i didnt delete a single message from our dms.<br>\nYou actually did dm me smth couple of times and deleted it.</p>","canEdit":false,"canDelete":false,"canHide":false,"canLike":true,"canFlag":true,"isApproved":true,"canApprove":false,"canReact":true},"relationships":{"user":{"data":{"type":"users","id":"3257"}},"discussion":{"data":{"type":"discussions","id":"578"}},"likes":{"data":[]},"mentionedBy":{"data":[{"type":"posts","id":"17302"}]},"reactions":{"data":[]}}},"included":[{"type":"users","id":"3257","attributes":{"username":"RumGuru","displayName":"RumGuru","avatarUrl":"https://drama.gg/assets/avatars/LfdbF5Ex7oM05L6h.png","slug":"RumGuru","joinTime":"2021-03-25T07:43:10+00:00","discussionCount":6,"commentCount":465,"canEdit":false,"canDelete":false,"lastSeenAt":"2022-03-20T12:49:12+00:00","canSuspend":false,"canEditPolls":false,"canStartPolls":true,"canSelfEditPolls":true,"canVotePolls":true,"cover":null,"cover_thumbnail":null,"canSetProfileCover":false,"canEditOwnNickname":false,"bio":null,"canViewBio":true,"canEditBio":false},"relationships":{"groups":{"data":[]}}},{"type":"users","id":"3731","attributes":{"username":"ShamsPlays","displayName":"ShamsPlays","avatarUrl":"https://drama.gg/assets/avatars/ROn0aZ8RF7gB3kby.png","slug":"ShamsPlays"}},{"type":"discussions","id":"578","attributes":{"title":"OTA - Hosting - ShamsPlays#2200/no tos&pp/lying about nodes/free domain.","slug":"578-ota-hosting-shamsplays2200no-tospplying-about-nodesfree-domain","isApproved":true}},{"type":"posts","id":"17302","attributes":{"number":64,"createdAt":"2021-05-29T20:46:09+00:00","contentType":"comment","contentHtml":"<p><a href=\"https://drama.gg/d/578/61\" class=\"PostMention\" data-id=\"17299\">RumGuru</a> Hes stupid because he caught you? Bitch please, the guy you were supporting demoted you right in front of my eyes, Even thunderx doesn't trust you because we already knew what your intentions were. btw, How were you going to improve the server by getting access to our domain and staff panel? Please tell, I am dying to hear your lame coverups.</p>"},"relationships":{"user":{"data":{"type":"users","id":"3731"}},"discussion":{"data":{"type":"discussions","id":"578"}}}}]}