{"data":{"type":"posts","id":"25638","attributes":{"number":18,"createdAt":"2021-08-25T03:12:37+00:00","contentType":"comment","contentHtml":"<p><img src=\"https://drama.gg/assets/files/2021-08-25/1629861111-20292-image.png\" title=\"\"><br>\n<img src=\"https://drama.gg/assets/files/2021-08-25/1629861124-999642-image.png\" title=\"\"><br>\n<img src=\"https://drama.gg/assets/files/2021-08-25/1629861133-677253-image.png\" title=\"\"><br>\n<img src=\"https://drama.gg/assets/files/2021-08-25/1629861143-519651-image.png\" title=\"\"><br>\n<img src=\"https://drama.gg/assets/files/2021-08-25/1629861153-150819-image.png\" title=\"\"></p>\n","canEdit":false,"canDelete":false,"canHide":false,"canLike":true,"canFlag":true,"isApproved":true,"canApprove":false,"canReact":true},"relationships":{"user":{"data":{"type":"users","id":"4026"}},"discussion":{"data":{"type":"discussions","id":"917"}},"likes":{"data":[]},"mentionedBy":{"data":[]},"reactions":{"data":[]}}},"included":[{"type":"users","id":"4026","attributes":{"username":"IoNetty","displayName":"IoNetty","avatarUrl":"https://drama.gg/assets/avatars/bxpKLp1Y6DahxxDT.png","slug":"IoNetty","joinTime":"2021-07-21T13:07:55+00:00","discussionCount":4,"commentCount":247,"canEdit":false,"canDelete":false,"lastSeenAt":"2022-04-02T02:26:55+00:00","canSuspend":false,"canEditPolls":false,"canStartPolls":true,"canSelfEditPolls":true,"canVotePolls":true,"cover":null,"cover_thumbnail":null,"canSetProfileCover":false,"canEditOwnNickname":false,"bio":"","canViewBio":true,"canEditBio":false},"relationships":{"groups":{"data":[]}}},{"type":"discussions","id":"917","attributes":{"title":"DangoWebHosting","slug":"917-dangowebhosting","isApproved":true}}]}