{"data":{"type":"posts","id":"36801","attributes":{"number":1759,"createdAt":"2021-12-03T19:57:32+00:00","contentType":"comment","contentHtml":"<p><a href=\"https://drama.gg/d/34/1756\" class=\"PostMention\" data-id=\"36798\">Falix_Lily</a> you dont have my bank card, never asked for information that correlates to the bank card in the first place. and never sent an email that supposedly went through</p>\n\n<p>ps: my bank has a portion of the logs for upcoming transactions where refunds are shown as issued under pending until the balance actually comes through.</p>\n\n<p>on my bank, theres nothing there.</p>","canEdit":false,"canDelete":false,"canHide":false,"canLike":true,"canFlag":true,"isApproved":true,"canApprove":false,"canReact":true},"relationships":{"user":{"data":{"type":"users","id":"4993"}},"discussion":{"data":{"type":"discussions","id":"34"}},"likes":{"data":[]},"mentionedBy":{"data":[{"type":"posts","id":"36803"}]},"reactions":{"data":[]}}},"included":[{"type":"users","id":"4993","attributes":{"username":"whosthisagain","displayName":"whosthisagain","avatarUrl":"https://drama.gg/assets/avatars/1HGmNQBvk7KoBZgo.png","slug":"whosthisagain","joinTime":"2021-12-03T18:14:44+00:00","discussionCount":0,"commentCount":11,"canEdit":false,"canDelete":false,"lastSeenAt":"2021-12-03T20:21:13+00:00","canSuspend":false,"canEditPolls":false,"canStartPolls":true,"canSelfEditPolls":true,"canVotePolls":true,"cover":null,"cover_thumbnail":null,"canSetProfileCover":false,"canEditOwnNickname":false,"bio":null,"canViewBio":true,"canEditBio":false},"relationships":{"groups":{"data":[]}}},{"type":"users","id":"4994","attributes":{"username":"Falix_Lily","displayName":"Falix_Lily","avatarUrl":null,"slug":"Falix_Lily"}},{"type":"discussions","id":"34","attributes":{"title":"Lamaker/ItzAwesome/Lily/Pamar | FalixNodes/Falix.gg & PrimeSRV","slug":"34-lamakeritzawesomelilypamar-falixnodesfalixgg-primesrv","isApproved":true}},{"type":"posts","id":"36803","attributes":{"number":1761,"createdAt":"2021-12-03T20:03:35+00:00","contentType":"comment","contentHtml":"<p><a href=\"https://drama.gg/d/34/1759\" class=\"PostMention\" data-id=\"36801\">whosthisagain</a> We use payment processor Stripe, they take care of payments and in their dashboard we can view your latest payments, invoices and subscriptions, we do not need to know your full bank card details just to find your payment, simple email address is enough.</p>\n\n<p>Regarding the refunds, instant is only possible if it was only pre-authorized I believe, but since your bank card has been captured for the payment, it may take time for our payment processor and your bank to process the refund to your bank card. You can find more information on how refunds works in the search engine.</p>"},"relationships":{"user":{"data":{"type":"users","id":"4994"}},"discussion":{"data":{"type":"discussions","id":"34"}}}}]}