{"data":{"type":"posts","id":"49224","attributes":{"number":28,"createdAt":"2022-11-09T18:35:58+00:00","contentType":"comment","contentHtml":"<p><a href=\"https://drama.gg/d/2070/23\" class=\"PostMention\" data-id=\"49219\">khootieexd</a> Shut up your owners team is just so dumb get a life of yourself cunt you are like a 5 year old also dont go starting shit and your owner called Latvis is a little cunt retarded person I cannot make this into a reply to you and you better fuck off rat hope your community dies.</p>\n\n<p>Cam</p>","canEdit":false,"canDelete":false,"canHide":false,"canLike":true,"canFlag":true,"isApproved":true,"canApprove":false,"canReact":true},"relationships":{"user":{"data":{"type":"users","id":"6976"}},"discussion":{"data":{"type":"discussions","id":"2070"}},"likes":{"data":[]},"mentionedBy":{"data":[{"type":"posts","id":"49225"}]},"reactions":{"data":[]}}},"included":[{"type":"users","id":"6976","attributes":{"username":"BeansCam","displayName":"BeansCam","avatarUrl":"https://drama.gg/assets/avatars/0nbn7fChPFPL985x.png","slug":"BeansCam","joinTime":"2022-11-09T18:23:17+00:00","discussionCount":1,"commentCount":10,"canEdit":false,"canDelete":false,"lastSeenAt":"2023-04-20T06:15:26+00:00","canSuspend":false,"canEditPolls":false,"canStartPolls":true,"canSelfEditPolls":true,"canVotePolls":true,"cover":null,"cover_thumbnail":null,"canSetProfileCover":false,"canEditOwnNickname":false},"relationships":{"groups":{"data":[]}}},{"type":"users","id":"6975","attributes":{"username":"alvapepsi","displayName":"alvapepsi","avatarUrl":"https://drama.gg/assets/avatars/Yz8WeIqCTodEnJvE.png","slug":"alvapepsi"}},{"type":"discussions","id":"2070","attributes":{"title":"khootiee aka Crac, being a dick and unprofessional ","slug":"2070-khootiee-aka-crac-being-a-dick-and-unprofessional","isApproved":true}},{"type":"posts","id":"49225","attributes":{"number":29,"createdAt":"2022-11-09T18:36:53+00:00","contentType":"comment","contentHtml":"<p><a href=\"https://drama.gg/d/2070/28\" class=\"PostMention\" data-id=\"49224\">BeansCam</a> i wouldnt call it a community, i would call it a server full of dipshits</p>"},"relationships":{"user":{"data":{"type":"users","id":"6975"}},"discussion":{"data":{"type":"discussions","id":"2070"}}}}]}