{"data":{"type":"posts","id":"5196","attributes":{"number":194,"createdAt":"2021-01-26T18:12:34+00:00","contentType":"comment","contentHtml":"<p><a href=\"https://drama.gg/d/154/192\" class=\"PostMention\" data-id=\"5194\">ItzToxicYT</a> your reason was: Saini offerd somthing else</p> ","canEdit":false,"canDelete":false,"canHide":false,"canLike":true,"canFlag":true,"isApproved":true,"canApprove":false,"canReact":true},"relationships":{"user":{"data":{"type":"users","id":"80"}},"discussion":{"data":{"type":"discussions","id":"154"}},"likes":{"data":[]},"mentionedBy":{"data":[{"type":"posts","id":"5197"},{"type":"posts","id":"5199"}]},"reactions":{"data":[]}}},"included":[{"type":"users","id":"80","attributes":{"username":"JAY","displayName":"JAY","avatarUrl":null,"slug":"JAY","joinTime":"2020-08-13T20:44:57+00:00","discussionCount":8,"commentCount":122,"canEdit":false,"canDelete":false,"lastSeenAt":"2021-11-19T23:40:25+00:00","canSuspend":false,"canEditPolls":false,"canStartPolls":true,"canSelfEditPolls":true,"canVotePolls":true,"cover":null,"cover_thumbnail":null,"canSetProfileCover":false,"canEditOwnNickname":false,"bio":"Roses are red violets are blue I'd like to say hi too you","canViewBio":true,"canEditBio":false},"relationships":{"groups":{"data":[]}}},{"type":"users","id":"105","attributes":{"username":"AbisGamer","displayName":"AbisGamer","avatarUrl":"https://drama.gg/assets/avatars/r3CIX0CHVOcDltkB.png","slug":"AbisGamer"}},{"type":"users","id":"3047","attributes":{"username":"ItzToxicYT","displayName":"ItzToxicYT","avatarUrl":null,"slug":"ItzToxicYT"}},{"type":"discussions","id":"154","attributes":{"title":"NavoHosting-Scammers-Griefers-TiltedHost Resellers","slug":"154-navohosting-scammers-griefers-tiltedhost-resellers","isApproved":true}},{"type":"posts","id":"5197","attributes":{"number":195,"createdAt":"2021-01-26T18:15:16+00:00","contentType":"comment","contentHtml":"<p><a href=\"https://drama.gg/d/154/194\" class=\"PostMention\" data-id=\"5196\">JAY</a> How about explain why you didn't do thus back in November instead of saying you won't or that you lost it <img src=\"https://winterhoax.com/assets/files/2021-01-26/1611684911-601144-20210126-191119.jpg\" title=\"\"></p>\n"},"relationships":{"user":{"data":{"type":"users","id":"105"}},"discussion":{"data":{"type":"discussions","id":"154"}}}},{"type":"posts","id":"5199","attributes":{"number":197,"createdAt":"2021-01-26T18:20:50+00:00","contentType":"comment","contentHtml":"<p><a href=\"https://drama.gg/d/154/194\" class=\"PostMention\" data-id=\"5196\">JAY</a> I was never meant to buy your scam host, that payment WASN'T PAID FOR YOUR HOSTING, it was decided later. When u told me you were gonna give Unlimited spaces. But then, u changed the whole subject. The reason wasn't only Saini offered me his help, it was because I cannot trust a man who changes the whole subject to eat a bit more cents.</p>"},"relationships":{"user":{"data":{"type":"users","id":"3047"}},"discussion":{"data":{"type":"discussions","id":"154"}}}}]}