{"data":{"type":"posts","id":"5813","attributes":{"number":388,"createdAt":"2021-02-04T09:58:55+00:00","contentType":"comment","contentHtml":"<p>no</p>","canEdit":false,"canDelete":false,"canHide":false,"canLike":true,"canFlag":true,"isApproved":true,"canApprove":false,"canReact":true},"relationships":{"discussion":{"data":{"type":"discussions","id":"122"}},"likes":{"data":[{"type":"users","id":"30"}]},"mentionedBy":{"data":[{"type":"posts","id":"5814"},{"type":"posts","id":"5816"}]},"reactions":{"data":[]}}},"included":[{"type":"discussions","id":"122","attributes":{"title":"ViaHost, Sryden, ExoHost, AltHost, HelioNodes, BlockNode | Bad/Layer","slug":"122-viahost-sryden-exohost-althost-helionodes-blocknode-badlayer","isApproved":true}},{"type":"users","id":"30","attributes":{"username":"Triassic","displayName":"Triassic","avatarUrl":"https://drama.gg/assets/avatars/vpuY80JJaf7LHX7q.png","slug":"Triassic"}},{"type":"users","id":"2846","attributes":{"username":"Tomas","displayName":"Tomas","avatarUrl":"https://drama.gg/assets/avatars/Q5hYhqTjdnQtMn8K.png","slug":"Tomas"}},{"type":"users","id":"2871","attributes":{"username":"RusJS","displayName":"RusJS","avatarUrl":"https://drama.gg/assets/avatars/NlCiT9o37Teub04l.png","slug":"RusJS"}},{"type":"posts","id":"5814","attributes":{"number":389,"createdAt":"2021-02-04T09:59:49+00:00","contentType":"comment","contentHtml":"<p><a href=\"https://drama.gg/d/122/388\" class=\"PostMention\" data-id=\"5813\">badsk</a> Provide some proof that you've paid for all these accounts then, whilst you can't even pay for your own host.</p>"},"relationships":{"user":{"data":{"type":"users","id":"2846"}},"discussion":{"data":{"type":"discussions","id":"122"}}}},{"type":"posts","id":"5816","attributes":{"number":391,"createdAt":"2021-02-04T10:04:10+00:00","contentType":"comment","contentHtml":"<p><a href=\"https://drama.gg/d/122/388\" class=\"PostMention\" data-id=\"5813\">badsk</a> yes</p>"},"relationships":{"user":{"data":{"type":"users","id":"2871"}},"discussion":{"data":{"type":"discussions","id":"122"}}}}]}