{"data":{"type":"posts","id":"7554","attributes":{"number":91,"createdAt":"2021-03-01T13:11:50+00:00","contentType":"comment","contentHtml":"<p><a href=\"https://drama.gg/d/231/90\" class=\"PostMention\" data-id=\"7553\">Two</a> I believe that banning a user with no other reason than for their existence is a winterhoaxable offense.</p>","canEdit":false,"canDelete":false,"canHide":false,"canLike":true,"canFlag":true,"isApproved":true,"canApprove":false,"canReact":true},"relationships":{"user":{"data":{"type":"users","id":"3036"}},"discussion":{"data":{"type":"discussions","id":"231"}},"likes":{"data":[]},"mentionedBy":{"data":[{"type":"posts","id":"7556"}]},"reactions":{"data":[]}}},"included":[{"type":"users","id":"3036","attributes":{"username":"Vanquish","displayName":"Vanquish","avatarUrl":"https://drama.gg/assets/avatars/fggUflkAbpVpGb63.png","slug":"Vanquish","joinTime":"2021-01-24T17:51:40+00:00","discussionCount":14,"commentCount":360,"canEdit":false,"canDelete":false,"lastSeenAt":"2021-06-02T04:07:54+00:00","canSuspend":false,"canEditPolls":false,"canStartPolls":true,"canSelfEditPolls":true,"canVotePolls":true,"cover":null,"cover_thumbnail":null,"canSetProfileCover":false,"canEditOwnNickname":false,"bio":"i do stuff","canViewBio":true,"canEditBio":false},"relationships":{"groups":{"data":[]}}},{"type":"users","id":"3073","attributes":{"username":"Bxrk","displayName":"Bxrk","avatarUrl":"https://drama.gg/assets/avatars/tQjbyBSC297Wf1Md.png","slug":"Bxrk"}},{"type":"discussions","id":"231","attributes":{"title":"BombHost | Unprofessional","slug":"231-bombhost-unprofessional","isApproved":true}},{"type":"posts","id":"7556","attributes":{"number":93,"createdAt":"2021-03-01T13:12:45+00:00","contentType":"comment","contentHtml":"<p><a href=\"https://drama.gg/d/231/91\" class=\"PostMention\" data-id=\"7554\">Vanquish</a> lix got banned for no reason i think idk</p> "},"relationships":{"user":{"data":{"type":"users","id":"3073"}},"discussion":{"data":{"type":"discussions","id":"231"}}}}]}